{
  "toolName": "energy-peak-cost",
  "inputs": [
    {
      "id": "peakDemand",
      "label": "Peak Demand",
      "type": "number",
      "unit": "kW",
      "default": 100,
      "min": 0,
      "max": 100000,
      "options": null,
      "businessContext": "Maximum power demand during billing period. Based on utility meter readings. ISO 50001 energy management standard."
    },
    {
      "id": "peakRate",
      "label": "Peak Rate",
      "type": "number",
      "unit": "$/kW",
      "default": 10,
      "min": 0,
      "max": 1000,
      "options": null,
      "businessContext": "Utility tariff rate for peak demand charges. Typically from utility contract or published tariffs."
    },
    {
      "id": "billingPeriod",
      "label": "Billing Period",
      "type": "select",
      "unit": "",
      "default": "monthly",
      "min": null,
      "max": null,
      "options": [
        "monthly",
        "quarterly",
        "annually"
      ],
      "businessContext": "Frequency of billing cycle. Determines cost scaling. Common utility practice."
    },
    {
      "id": "peakHours",
      "label": "Peak Hours per Day",
      "type": "number",
      "unit": "hours",
      "default": 4,
      "min": 0,
      "max": 24,
      "options": null,
      "businessContext": "Number of hours per day considered peak. Defined by utility or ISO 50001 peak load management."
    },
    {
      "id": "operatingDays",
      "label": "Operating Days per Period",
      "type": "number",
      "unit": "days",
      "default": 22,
      "min": 1,
      "max": 365,
      "options": null,
      "businessContext": "Number of days facility operates in billing period. Used for energy cost allocation. Industry standard."
    },
    {
      "id": "energyPrice",
      "label": "Energy Price",
      "type": "number",
      "unit": "$/kWh",
      "default": 0.12,
      "min": 0,
      "max": 10,
      "options": null,
      "businessContext": "Cost per kWh for energy consumed. From utility tariff. ISO 50001 energy cost analysis."
    },
    {
      "id": "loadFactor",
      "label": "Load Factor",
      "type": "number",
      "unit": "%",
      "default": 70,
      "min": 0,
      "max": 100,
      "options": null,
      "businessContext": "Ratio of average load to peak load. Indicates efficiency. Industry benchmark for demand management."
    },
    {
      "id": "dataConfidence",
      "label": "Data Confidence",
      "type": "select",
      "unit": "",
      "default": "medium",
      "min": null,
      "max": null,
      "options": [
        "low",
        "medium",
        "high"
      ],
      "businessContext": "Quality of input data. Affects confidence adjustment. Common in financial analysis."
    }
  ],
  "validation": {
    "rules": [
      "peakDemand > 0",
      "peakRate > 0",
      "peakHours >= 0 and peakHours <= 24",
      "operatingDays > 0",
      "energyPrice > 0",
      "loadFactor >= 0 and loadFactor <= 100"
    ],
    "thresholds": {
      "loadFactor < 50": "Low load factor indicates inefficient peak usage; consider demand reduction strategies.",
      "peakDemand > 500": "High peak demand may trigger additional utility surcharges."
    }
  },
  "formulas": {
    "peakCost": "peakDemand * peakRate * (billingPeriod === 'monthly' ? 1 : billingPeriod === 'quarterly' ? 3 : 12)",
    "energyCost": "peakDemand * loadFactor / 100 * peakHours * operatingDays * energyPrice * (billingPeriod === 'monthly' ? 1 : billingPeriod === 'quarterly' ? 3 : 12)",
    "totalCost": "peakCost + energyCost",
    "costPerUnit": "totalCost / (peakDemand * loadFactor / 100 * peakHours * operatingDays)",
    "dataConfidenceAdjusted": "totalCost * (dataConfidence === 'low' ? 1.2 : dataConfidence === 'medium' ? 1.0 : 0.9)"
  },
  "outputs": {
    "primary": "totalCost",
    "breakdown": {
      "peakCost": "peakCost",
      "energyCost": "energyCost",
      "costPerUnit": "costPerUnit"
    },
    "hiddenLossDrivers": [
      "loadFactor < 50 ? 'Low load factor' : null",
      "peakDemand > 500 ? 'High peak demand' : null"
    ],
    "suggestedActions": [
      "Implement peak shaving strategies (e.g., load shifting, battery storage).",
      "Improve load factor by smoothing demand profile.",
      "Negotiate lower peak rate with utility provider.",
      "Consider energy efficiency upgrades to reduce overall consumption."
    ],
    "dataConfidenceAdjusted": "dataConfidenceAdjusted"
  },
  "premiumFeatures": [
    "PDF export",
    "CSV export",
    "Trend analysis over multiple periods",
    "Comparison with industry benchmarks",
    "Detailed breakdown report"
  ],
  "premiumRequired": true
}
