{
  "toolName": "sensitivity-specificity-calculator",
  "inputs": [
    {
      "id": "truePositive",
      "label": "Doğru Pozitif (DP)",
      "type": "number",
      "unit": "adet",
      "default": 80,
      "businessContext": "Testin pozitif olarak belirlediği gerçek pozitif vaka sayısı.",
      "label_i18n": {
        "en": "Doğru Pozitif (DP)",
        "tr": "Doğru Pozitif (DP)",
        "de": "Doğru Pozitif (DP)",
        "fr": "Doğru Pozitif (DP)",
        "es": "Doğru Pozitif (DP)",
        "ar": "Doğru Pozitif (DP)"
      }
    },
    {
      "id": "falsePositive",
      "label": "Yanlış Pozitif (YP)",
      "type": "number",
      "unit": "adet",
      "default": 20,
      "businessContext": "Testin pozitif olarak belirlediği fakat gerçekte negatif olan vaka sayısı.",
      "label_i18n": {
        "en": "Yanlış Pozitif (YP)",
        "tr": "Yanlış Pozitif (YP)",
        "de": "Yanlış Pozitif (YP)",
        "fr": "Yanlış Pozitif (YP)",
        "es": "Yanlış Pozitif (YP)",
        "ar": "Yanlış Pozitif (YP)"
      }
    },
    {
      "id": "falseNegative",
      "label": "Yanlış Negatif (YN)",
      "type": "number",
      "unit": "adet",
      "default": 10,
      "businessContext": "Testin negatif olarak belirlediği fakat gerçekte pozitif olan vaka sayısı.",
      "label_i18n": {
        "en": "Yanlış Negatif (YN)",
        "tr": "Yanlış Negatif (YN)",
        "de": "Yanlış Negatif (YN)",
        "fr": "Yanlış Negatif (YN)",
        "es": "Yanlış Negatif (YN)",
        "ar": "Yanlış Negatif (YN)"
      }
    },
    {
      "id": "trueNegative",
      "label": "Doğru Negatif (DN)",
      "type": "number",
      "unit": "adet",
      "default": 90,
      "businessContext": "Testin negatif olarak belirlediği gerçek negatif vaka sayısı.",
      "label_i18n": {
        "en": "Doğru Negatif (DN)",
        "tr": "Doğru Negatif (DN)",
        "de": "Doğru Negatif (DN)",
        "fr": "Doğru Negatif (DN)",
        "es": "Doğru Negatif (DN)",
        "ar": "Doğru Negatif (DN)"
      }
    }
  ],
  "formulas": {
    "sensitivity": "truePositive / (truePositive + falseNegative)",
    "specificity": "trueNegative / (trueNegative + falsePositive)",
    "ppv": "truePositive / (truePositive + falsePositive)",
    "npv": "trueNegative / (trueNegative + falseNegative)",
    "accuracy": "(truePositive + trueNegative) / (truePositive + falsePositive + falseNegative + trueNegative)"
  },
  "outputs": {
    "primary": "sensitivity",
    "breakdown": [
      "specificity",
      "ppv",
      "npv",
      "accuracy"
    ],
    "hiddenLossDrivers": [],
    "suggestedActions": [
      "Review inputs and verify results against site standards."
    ],
    "dataConfidenceAdjusted": "accuracy"
  },
  "category": "Üretim & İmalat",
  "sector": "Üretim & İmalat",
  "premiumRequired": false,
  "catalogCategory": "everyday-life",
  "sectorSlug": "daily-renovation",
  "categorySlug": "technology-ai-cloud-cyber",
  "sectorId": "diger",
  "profession": "Genel Uzman",
  "categoryId": "diger",
  "validation": {
    "rules": [],
    "thresholds": {}
  },
  "premiumFeatures": []
}
